alibabacloud_fc_open20210406/__init__.py
alibabacloud_fc_open20210406/client.py
alibabacloud_fc_open20210406/models.py
alibabacloud_fc_open20210406_py2-2.0.11.dist-info/LICENSE
alibabacloud_fc_open20210406_py2-2.0.11.dist-info/METADATA
alibabacloud_fc_open20210406_py2-2.0.11.dist-info/WHEEL
alibabacloud_fc_open20210406_py2-2.0.11.dist-info/top_level.txt
alibabacloud_fc_open20210406_py2-2.0.11.dist-info/RECORD
